LICENSE
README.md
pyproject.toml
setup.py
cobo_custody/__init__.py
cobo_custody.egg-info/PKG-INFO
cobo_custody.egg-info/SOURCES.txt
cobo_custody.egg-info/dependency_links.txt
cobo_custody.egg-info/requires.txt
cobo_custody.egg-info/top_level.txt
cobo_custody/client/__init__.py
cobo_custody/client/api_response.py
cobo_custody/client/client.py
cobo_custody/client/mpc_client.py
cobo_custody/client/mpc_prime_broker_client.py
cobo_custody/client/web3_client.py
cobo_custody/config/__init__.py
cobo_custody/config/env.py
cobo_custody/error/__init__.py
cobo_custody/error/api_error.py
cobo_custody/model/__init__.py
cobo_custody/model/enums.py
cobo_custody/signer/__init__.py
cobo_custody/signer/api_signer.py
cobo_custody/signer/local_signer.py