Metadata-Version: 2.1
Name: cobo-custody
Version: 0.46
Summary: Cobo Custody restful api
Home-page: https://github.com/CoboGlobal/cobo-python-api
Author: Cobo
Author-email: support@cobo.com
License: Cobo Copyright Reserved
Platform: UNKNOWN
Requires-Python: >=3.7
License-File: LICENSE
